setup.py
fortigateconf/__init__.py
fortigateconf/fortigateconf.py
fortigateconf/fortigatemon.py
fortigateconf/testapi.py
fortigateconf/testssh.py
fortigateconf.egg-info/PKG-INFO
fortigateconf.egg-info/SOURCES.txt
fortigateconf.egg-info/dependency_links.txt
fortigateconf.egg-info/requires.txt
fortigateconf.egg-info/top_level.txt