Metadata-Version: 1.0
Name: fortigateconf
Version: 0.4.3
Summary: Python modules to interact with Fortigate configuration rest and ssh
Home-page: https://github.com/thomnico/fortigateconf
Author: Nicolas Thomas
Author-email: nthomas@fortinet.com
License: UNKNOWN
Platform: UNKNOWN
